aws_handler_decorators.py
Log_Api/__init__.py
Log_Api/Class/Database.py
Log_Api/Class/LogAPI.py
Log_Api/Class/__init__.py
Log_Api/Class/response..py
Log_Api/Models/LogAPI.py
Log_Api/Models/__init__.py
Log_Api-0.1.dist-info/METADATA
Log_Api-0.1.dist-info/WHEEL
Log_Api-0.1.dist-info/top_level.txt
Log_Api-0.1.dist-info/RECORD
