Metadata-Version: 2.1
Name: Log-Api
Version: 0.1
Summary: Paquete para el manejo de logs de apis aws lambda serverles con sqlalchemy
Home-page: https://github.com/1kagro/serverless-sqlalchemy-logapi
Author: Fabian Lozano
Author-email: fabianlozano044@gmail.com
License: MIT
Requires-Dist: SQLAlchemy
Requires-Dist: pymysql
Requires-Dist: jsonschema
Requires-Dist: boto3
Requires-Dist: urllib3
